Workbook

Sheet Assumptions
B1: JobValue Index Model For Bay Area SWE
B3: Assumptions Sheet
E4: Luffy
B5: Basic | C5: Company Name | D5: String | E5: Zoom
C6: Job Level | D6: String | E6: ZP3
C7: Work Location Zip Code | D7: City/Town | E7: 95113
C8: Is Onsite | D8: Yes/No | E8: Yes
C9: Tax Filling Status | E9: Single
B11: Revenue | C11: Base Salary | D11: $/Year | E11: 178000
C12: Target Bonus Pct | D12: % | E12: 15
C13: RSU Per Year | D13: $/Year | E13: 20000
C14: Sign on Bonus | D14: $ | E14: 10000
B16: COGS | C16: Living Location Zip Code | D16: Zip Code | E16: 95014
C17: Override Monthly Rent | D17: $/Month | E17: 3950
C18: Override Monthly Living Cost | D18: $/Month | E18: 1700
C19: Commute Days per Week | D19: Days/Week | E19: 4
C20: Commute Time | D20: Hours/Day | E20: 0.8
B22: Discount Rate | C22: Actual Working Hours | D22: Hours/Week | E22: 50
C23: PTO Days | D23: Days/Year | E23: 17
C24: Manage Support Score | D24: 1-5 Scale | E24: 4
C25: Team Culture Score | D25: 1-5 Scale | E25: 4
C26: Org Stability Score | D26: 1-5 Scale | E26: 4
B28: Utility Weight | C28: Financial | D28: % | E28: 50
C29: WLB | D29: % | E29: 40
C30: Company Vibe | D30: % | E30: 10
B31: Weight Check | E31: =SUM(E28:E30) -> 100

Sheet Market_Comps
B2: Firm Tier and Level | J2: Mapping Dictionary | N2: Cost of Living (Per Month) | V2: Federal income tax rates | Z2: Federal income tax rates
B3: Tier | C3: Firm | D3: Level | E3: Median TC | J3: Firm | K3: FirmLevel | L3: StardandLevel | N3: Zip Code | O3: Avg Rent | P3: Avg Living Cost | Q3: COLI Multiplier | V3: From | W3: To | X3: Rate | Z3: From | AA3: To | AB3: Rate
B4: S | C4: Apple | D4: Entry (L3) | E4: 183925 | J4: Zoom | K4: ZP1 | L4: Entry (L3) | N4: 94301 | O4: 3600 | P4: 1500 | Q4: 1.2 | S4: Bay Area Retention Rate | T4: 0.62 | V4: Single | Z4: Single
B5: S | C5: Apple | D5: Mid (L4) | E5: 235361 | J5: Zoom | K5: ZP2 | L5: Mid (L4) | N5: 94303 | O5: 3600 | P5: 1500 | Q5: 1.2 | S5: Standard Weekly Hours | T5: 40 | V5: 0 | W5: 11925 | X5: 0.1 | Z5: 0 | AA5: 11079 | AB5: 0.01
B6: S | C6: Apple | D6: Senior (L5) | E6: 343425 | J6: Zoom | K6: ZP3 | L6: Senior (L5) | N6: 94304 | O6: 3600 | P6: 1500 | Q6: 1.2 | S6: Best Working Hours | T6: 2080 | V6: 11926 | W6: 48475 | X6: 0.12 | Z6: 11926 | AA6: 48475 | AB6: 0.12
B7: S | C7: Apple | D7: Staff (L6) | E7: 582078 | J7: Zoom | K7: ZP4 | L7: Staff (L6) | N7: 94305 | O7: 3600 | P7: 1500 | Q7: 1.2 | V7: 48476 | W7: 103350 | X7: 0.22 | Z7: 48476 | AA7: 103350 | AB7: 0.22
B8: S | C8: Apple | D8: Principal (L7) | E8: 795350 | J8: Zoom | K8: ZP5 | L8: Principal (L7) | N8: 94306 | O8: 3600 | P8: 1500 | Q8: 1.2 | V8: 103351 | W8: 197300 | X8: 0.24 | Z8: 103351 | AA8: 197300 | AB8: 0.24
B9: S | C9: Google | D9: Entry (L3) | E9: 202120 | J9: Meta | K9: E3 | L9: Entry (L3) | N9: 95014 | O9: 3600 | P9: 1500 | Q9: 1.2 | V9: 197301 | W9: 250525 | X9: 0.32 | Z9: 197301 | AA9: 250525 | AB9: 0.32
B10: S | C10: Google | D10: Mid (L4) | E10: 293510 | J10: Meta | K10: E4 | L10: Mid (L4) | N10: 95015 | O10: 3600 | P10: 1500 | Q10: 1.2 | V10: 250526 | W10: 626350 | X10: 0.35 | Z10: 250526 | AA10: 626350 | AB10: 0.35
B11: S | C11: Google | D11: Senior (L5) | E11: 420262 | J11: Meta | K11: E5 | L11: Senior (L5) | N11: 94040 | O11: 3540 | P11: 1500 | Q11: 1.2 | V11: 626351 | W11: And Up | X11: 0.37 | Z11: 626351 | AA11: And Up | AB11: 0.37
B12: S | C12: Google | D12: Staff (L6) | E12: 567197 | J12: Meta | K12: E6 | L12: Staff (L6) | N12: 94041 | O12: 3540 | P12: 1500 | Q12: 1.2 | V12: Married filing jointly or qualifying surviving spouse | Z12: Married filing jointly or qualifying surviving spouse
B13: S | C13: Google | D13: Principal (L7) | E13: 900365 | J13: Meta | K13: E7 | L13: Principal (L7) | N13: 94043 | O13: 3540 | P13: 1500 | Q13: 1.2
B14: S | C14: Nvidia | D14: Entry (L3) | E14: {=_xlfn.IFS(B14="S", 200000, B14="A", 160000, B14="B", 130000) * _xlfn.IFS(D14="Entry (L3)", 0.8, D14="Mid (L4)", 1, D14="Senior (L5)", 1.4, D14="Staff (L6)", 1.8, D14="Principal (L7)", 2.5)} -> 160000 | J14: Apple | K14: ICT2 | L14: Entry (L3) | N14: 94022 | O14: 3177 | P14: 1500 | Q14: 1.2 | V14: 0 | W14: 23850 | X14: 0.1 | Z14: 0 | AA14: 23850 | AB14: 0.1
B15: S | C15: Nvidia | D15: Mid (L4) | E15: {=_xlfn.IFS(B15="S", 200000, B15="A", 160000, B15="B", 130000) * _xlfn.IFS(D15="Entry (L3)", 0.8, D15="Mid (L4)", 1, D15="Senior (L5)", 1.4, D15="Staff (L6)", 1.8, D15="Principal (L7)", 2.5)} -> 200000 | J15: Apple | K15: ICT3 | L15: Mid (L4) | N15: 94024 | O15: 3177 | P15: 1500 | Q15: 1.2 | V15: 23851 | W15: 96950 | X15: 0.12 | Z15: 23851 | AA15: 96950 | AB15: 0.12
B16: S | C16: Nvidia | D16: Senior (L5) | E16: {=_xlfn.IFS(B16="S", 200000, B16="A", 160000, B16="B", 130000) * _xlfn.IFS(D16="Entry (L3)", 0.8, D16="Mid (L4)", 1, D16="Senior (L5)", 1.4, D16="Staff (L6)", 1.8, D16="Principal (L7)", 2.5)} -> 280000 | J16: Apple | K16: ICT4 | L16: Senior (L5) | N16: 94085 | O16: 2616 | P16: 1500 | Q16: 1.1 | V16: 96951 | W16: 206700 | X16: 0.22 | Z16: 96951 | AA16: 206700 | AB16: 0.22
B17: S | C17: Nvidia | D17: Staff (L6) | E17: {=_xlfn.IFS(B17="S", 200000, B17="A", 160000, B17="B", 130000) * _xlfn.IFS(D17="Entry (L3)", 0.8, D17="Mid (L4)", 1, D17="Senior (L5)", 1.4, D17="Staff (L6)", 1.8, D17="Principal (L7)", 2.5)} -> 360000 | J17: Apple | K17: ICT5 | L17: Staff (L6) | N17: 94086 | O17: 2616 | P17: 1500 | Q17: 1.1 | V17: 206701 | W17: 394600 | X17: 0.24 | Z17: 206701 | AA17: 394600 | AB17: 0.24
B18: S | C18: Nvidia | D18: Principal (L7) | E18: {=_xlfn.IFS(B18="S", 200000, B18="A", 160000, B18="B", 130000) * _xlfn.IFS(D18="Entry (L3)", 0.8, D18="Mid (L4)", 1, D18="Senior (L5)", 1.4, D18="Staff (L6)", 1.8, D18="Principal (L7)", 2.5)} -> 500000 | J18: Apple | K18: ICT6 | L18: Principal (L7) | N18: 94087 | O18: 2616 | P18: 1500 | Q18: 1.1 | V18: 394601 | W18: 501050 | X18: 0.32 | Z18: 394601 | AA18: 501050 | AB18: 0.32
B19: S | C19: OpenAI | D19: Entry (L3) | E19: {=_xlfn.IFS(B19="S", 200000, B19="A", 160000, B19="B", 130000) * _xlfn.IFS(D19="Entry (L3)", 0.8, D19="Mid (L4)", 1, D19="Senior (L5)", 1.4, D19="Staff (L6)", 1.8, D19="Principal (L7)", 2.5)} -> 160000 | N19: 94089 | O19: 2616 | P19: 1500 | Q19: 1.1 | V19: 501051 | W19: 751600 | X19: 0.35 | Z19: 501051 | AA19: 751600 | AB19: 0.35
B20: S | C20: OpenAI | D20: Mid (L4) | E20: {=_xlfn.IFS(B20="S", 200000, B20="A", 160000, B20="B", 130000) * _xlfn.IFS(D20="Entry (L3)", 0.8, D20="Mid (L4)", 1, D20="Senior (L5)", 1.4, D20="Staff (L6)", 1.8, D20="Principal (L7)", 2.5)} -> 200000 | N20: 95050 | O20: 3300 | P20: 1500 | Q20: 1.1 | V20: 751601 | W20: And Up | X20: 0.37 | Z20: 751601 | AA20: And Up | AB20: 0.37
B21: S | C21: OpenAI | D21: Senior (L5) | E21: {=_xlfn.IFS(B21="S", 200000, B21="A", 160000, B21="B", 130000) * _xlfn.IFS(D21="Entry (L3)", 0.8, D21="Mid (L4)", 1, D21="Senior (L5)", 1.4, D21="Staff (L6)", 1.8, D21="Principal (L7)", 2.5)} -> 280000 | N21: 95051 | O21: 3300 | P21: 1500 | Q21: 1.1 | V21: Married filing separately | Z21: Married filing separately
B22: S | C22: OpenAI | D22: Staff (L6) | E22: {=_xlfn.IFS(B22="S", 200000, B22="A", 160000, B22="B", 130000) * _xlfn.IFS(D22="Entry (L3)", 0.8, D22="Mid (L4)", 1, D22="Senior (L5)", 1.4, D22="Staff (L6)", 1.8, D22="Principal (L7)", 2.5)} -> 360000 | N22: 95054 | O22: 3300 | P22: 1500 | Q22: 1.1 | V22: 0 | W22: 11925 | X22: 0.1 | Z22: 0 | AA22: 11925 | AB22: 0.1
B23: S | C23: OpenAI | D23: Principal (L7) | E23: {=_xlfn.IFS(B23="S", 200000, B23="A", 160000, B23="B", 130000) * _xlfn.IFS(D23="Entry (L3)", 0.8, D23="Mid (L4)", 1, D23="Senior (L5)", 1.4, D23="Staff (L6)", 1.8, D23="Principal (L7)", 2.5)} -> 500000 | N23: 95002 | O23: 2700 | P23: 1500 | Q23: 0.9 | V23: 11926 | W23: 48475 | X23: 0.12 | Z23: 11926 | AA23: 48475 | AB23: 0.12
B24: S | C24: Meta | D24: Entry (L3) | E24: 190591 | N24: 95110 | O24: 2700 | P24: 1500 | Q24: 0.9 | V24: 48476 | W24: 103350 | X24: 0.22 | Z24: 48476 | AA24: 103350 | AB24: 0.22
B25: S | C25: Meta | D25: Mid (L4) | E25: 325659 | N25: 95117 | O25: 2700 | P25: 1500 | Q25: 0.9 | V25: 103351 | W25: 197300 | X25: 0.24 | Z25: 103351 | AA25: 197300 | AB25: 0.24
B26: S | C26: Meta | D26: Senior (L5) | E26: 467175 | N26: 95126 | O26: 2700 | P26: 1500 | Q26: 0.9 | V26: 197301 | W26: 250525 | X26: 0.32 | Z26: 197301 | AA26: 250525 | AB26: 0.32
B27: S | C27: Meta | D27: Staff (L6) | E27: 792310 | N27: 95128 | O27: 2700 | P27: 1500 | Q27: 0.9 | V27: 250526 | W27: 375800 | X27: 0.35 | Z27: 250526 | AA27: 375800 | AB27: 0.35
B28: S | C28: Meta | D28: Principal (L7) | E28: 1449584 | N28: 95129 | O28: 2700 | P28: 1500 | Q28: 0.9 | V28: 375801 | W28: And Up | X28: 0.37 | Z28: 375801 | AA28: And Up | AB28: 0.37
B29: S | C29: Microsoft | D29: Entry (L3) | E29: {=_xlfn.IFS(B29="S", 200000, B29="A", 160000, B29="B", 130000) * _xlfn.IFS(D29="Entry (L3)", 0.8, D29="Mid (L4)", 1, D29="Senior (L5)", 1.4, D29="Staff (L6)", 1.8, D29="Principal (L7)", 2.5)} -> 160000 | N29: 95130 | O29: 2700 | P29: 1500 | Q29: 0.9
B30: S | C30: Microsoft | D30: Mid (L4) | E30: {=_xlfn.IFS(B30="S", 200000, B30="A", 160000, B30="B", 130000) * _xlfn.IFS(D30="Entry (L3)", 0.8, D30="Mid (L4)", 1, D30="Senior (L5)", 1.4, D30="Staff (L6)", 1.8, D30="Principal (L7)", 2.5)} -> 200000 | N30: 95131 | O30: 2700 | P30: 1500 | Q30: 0.9
B31: S | C31: Microsoft | D31: Senior (L5) | E31: {=_xlfn.IFS(B31="S", 200000, B31="A", 160000, B31="B", 130000) * _xlfn.IFS(D31="Entry (L3)", 0.8, D31="Mid (L4)", 1, D31="Senior (L5)", 1.4, D31="Staff (L6)", 1.8, D31="Principal (L7)", 2.5)} -> 280000 | N31: 95132 | O31: 2700 | P31: 1500 | Q31: 0.9
B32: S | C32: Microsoft | D32: Staff (L6) | E32: {=_xlfn.IFS(B32="S", 200000, B32="A", 160000, B32="B", 130000) * _xlfn.IFS(D32="Entry (L3)", 0.8, D32="Mid (L4)", 1, D32="Senior (L5)", 1.4, D32="Staff (L6)", 1.8, D32="Principal (L7)", 2.5)} -> 360000 | N32: 95133 | O32: 2700 | P32: 1500 | Q32: 0.9
B33: S | C33: Microsoft | D33: Principal (L7) | E33: {=_xlfn.IFS(B33="S", 200000, B33="A", 160000, B33="B", 130000) * _xlfn.IFS(D33="Entry (L3)", 0.8, D33="Mid (L4)", 1, D33="Senior (L5)", 1.4, D33="Staff (L6)", 1.8, D33="Principal (L7)", 2.5)} -> 500000 | N33: 95134 | O33: 2700 | P33: 1500 | Q33: 0.9
B34: S | C34: Amazon | D34: Entry (L3) | E34: {=_xlfn.IFS(B34="S", 200000, B34="A", 160000, B34="B", 130000) * _xlfn.IFS(D34="Entry (L3)", 0.8, D34="Mid (L4)", 1, D34="Senior (L5)", 1.4, D34="Staff (L6)", 1.8, D34="Principal (L7)", 2.5)} -> 160000 | N34: 95035 | O34: 3000 | P34: 1500 | Q34: 0.9
B35: S | C35: Amazon | D35: Mid (L4) | E35: {=_xlfn.IFS(B35="S", 200000, B35="A", 160000, B35="B", 130000) * _xlfn.IFS(D35="Entry (L3)", 0.8, D35="Mid (L4)", 1, D35="Senior (L5)", 1.4, D35="Staff (L6)", 1.8, D35="Principal (L7)", 2.5)} -> 200000 | N35: 95036 | O35: 3000 | P35: 1500 | Q35: 0.9
B36: S | C36: Amazon | D36: Senior (L5) | E36: {=_xlfn.IFS(B36="S", 200000, B36="A", 160000, B36="B", 130000) * _xlfn.IFS(D36="Entry (L3)", 0.8, D36="Mid (L4)", 1, D36="Senior (L5)", 1.4, D36="Staff (L6)", 1.8, D36="Principal (L7)", 2.5)} -> 280000
B37: S | C37: Amazon | D37: Staff (L6) | E37: {=_xlfn.IFS(B37="S", 200000, B37="A", 160000, B37="B", 130000) * _xlfn.IFS(D37="Entry (L3)", 0.8, D37="Mid (L4)", 1, D37="Senior (L5)", 1.4, D37="Staff (L6)", 1.8, D37="Principal (L7)", 2.5)} -> 360000
B38: S | C38: Amazon | D38: Principal (L7) | E38: {=_xlfn.IFS(B38="S", 200000, B38="A", 160000, B38="B", 130000) * _xlfn.IFS(D38="Entry (L3)", 0.8, D38="Mid (L4)", 1, D38="Senior (L5)", 1.4, D38="Staff (L6)", 1.8, D38="Principal (L7)", 2.5)} -> 500000
B39: S | C39: Netflix | D39: Entry (L3) | E39: {=_xlfn.IFS(B39="S", 200000, B39="A", 160000, B39="B", 130000) * _xlfn.IFS(D39="Entry (L3)", 0.8, D39="Mid (L4)", 1, D39="Senior (L5)", 1.4, D39="Staff (L6)", 1.8, D39="Principal (L7)", 2.5)} -> 160000
B40: S | C40: Netflix | D40: Mid (L4) | E40: {=_xlfn.IFS(B40="S", 200000, B40="A", 160000, B40="B", 130000) * _xlfn.IFS(D40="Entry (L3)", 0.8, D40="Mid (L4)", 1, D40="Senior (L5)", 1.4, D40="Staff (L6)", 1.8, D40="Principal (L7)", 2.5)} -> 200000
B41: S | C41: Netflix | D41: Senior (L5) | E41: {=_xlfn.IFS(B41="S", 200000, B41="A", 160000, B41="B", 130000) * _xlfn.IFS(D41="Entry (L3)", 0.8, D41="Mid (L4)", 1, D41="Senior (L5)", 1.4, D41="Staff (L6)", 1.8, D41="Principal (L7)", 2.5)} -> 280000
B42: S | C42: Netflix | D42: Staff (L6) | E42: {=_xlfn.IFS(B42="S", 200000, B42="A", 160000, B42="B", 130000) * _xlfn.IFS(D42="Entry (L3)", 0.8, D42="Mid (L4)", 1, D42="Senior (L5)", 1.4, D42="Staff (L6)", 1.8, D42="Principal (L7)", 2.5)} -> 360000
B43: S | C43: Netflix | D43: Principal (L7) | E43: {=_xlfn.IFS(B43="S", 200000, B43="A", 160000, B43="B", 130000) * _xlfn.IFS(D43="Entry (L3)", 0.8, D43="Mid (L4)", 1, D43="Senior (L5)", 1.4, D43="Staff (L6)", 1.8, D43="Principal (L7)", 2.5)} -> 500000
B44: S | C44: Airbnb | D44: Entry (L3) | E44: {=_xlfn.IFS(B44="S", 200000, B44="A", 160000, B44="B", 130000) * _xlfn.IFS(D44="Entry (L3)", 0.8, D44="Mid (L4)", 1, D44="Senior (L5)", 1.4, D44="Staff (L6)", 1.8, D44="Principal (L7)", 2.5)} -> 160000
B45: S | C45: Airbnb | D45: Mid (L4) | E45: {=_xlfn.IFS(B45="S", 200000, B45="A", 160000, B45="B", 130000) * _xlfn.IFS(D45="Entry (L3)", 0.8, D45="Mid (L4)", 1, D45="Senior (L5)", 1.4, D45="Staff (L6)", 1.8, D45="Principal (L7)", 2.5)} -> 200000
B46: S | C46: Airbnb | D46: Senior (L5) | E46: {=_xlfn.IFS(B46="S", 200000, B46="A", 160000, B46="B", 130000) * _xlfn.IFS(D46="Entry (L3)", 0.8, D46="Mid (L4)", 1, D46="Senior (L5)", 1.4, D46="Staff (L6)", 1.8, D46="Principal (L7)", 2.5)} -> 280000
B47: S | C47: Airbnb | D47: Staff (L6) | E47: {=_xlfn.IFS(B47="S", 200000, B47="A", 160000, B47="B", 130000) * _xlfn.IFS(D47="Entry (L3)", 0.8, D47="Mid (L4)", 1, D47="Senior (L5)", 1.4, D47="Staff (L6)", 1.8, D47="Principal (L7)", 2.5)} -> 360000
... B79: S | C79: JaneStreet | D79: Entry (L3) | E79: {=_xlfn.IFS(B79="S", 200000, B79="A", 160000, B79="B", 130000) * _xlfn.IFS(D79="Entry (L3)", 0.8, D79="Mid (L4)", 1, D79="Senior (L5)", 1.4, D79="Staff (L6)", 1.8, D79="Principal (L7)", 2.5)} -> 160000
B80: S | D80: Mid (L4) | E80: {=_xlfn.IFS(B80="S", 200000, B80="A", 160000, B80="B", 130000) * _xlfn.IFS(D80="Entry (L3)", 0.8, D80="Mid (L4)", 1, D80="Senior (L5)", 1.4, D80="Staff (L6)", 1.8, D80="Principal (L7)", 2.5)} -> 200000
B81: S | D81: Senior (L5) | E81: {=_xlfn.IFS(B81="S", 200000, B81="A", 160000, B81="B", 130000) * _xlfn.IFS(D81="Entry (L3)", 0.8, D81="Mid (L4)", 1, D81="Senior (L5)", 1.4, D81="Staff (L6)", 1.8, D81="Principal (L7)", 2.5)} -> 280000
B82: S | D82: Staff (L6) | E82: {=_xlfn.IFS(B82="S", 200000, B82="A", 160000, B82="B", 130000) * _xlfn.IFS(D82="Entry (L3)", 0.8, D82="Mid (L4)", 1, D82="Senior (L5)", 1.4, D82="Staff (L6)", 1.8, D82="Principal (L7)", 2.5)} -> 360000
B83: S | D83: Principal (L7) | E83: {=_xlfn.IFS(B83="S", 200000, B83="A", 160000, B83="B", 130000) * _xlfn.IFS(D83="Entry (L3)", 0.8, D83="Mid (L4)", 1, D83="Senior (L5)", 1.4, D83="Staff (L6)", 1.8, D83="Principal (L7)", 2.5)} -> 500000
B84: S | C84: HRT | D84: Entry (L3) | E84: {=_xlfn.IFS(B84="S", 200000, B84="A", 160000, B84="B", 130000) * _xlfn.IFS(D84="Entry (L3)", 0.8, D84="Mid (L4)", 1, D84="Senior (L5)", 1.4, D84="Staff (L6)", 1.8, D84="Principal (L7)", 2.5)} -> 160000
B85: S | D85: Mid (L4) | E85: {=_xlfn.IFS(B85="S", 200000, B85="A", 160000, B85="B", 130000) * _xlfn.IFS(D85="Entry (L3)", 0.8, D85="Mid (L4)", 1, D85="Senior (L5)", 1.4, D85="Staff (L6)", 1.8, D85="Principal (L7)", 2.5)} -> 200000
B86: S | D86: Senior (L5) | E86: {=_xlfn.IFS(B86="S", 200000, B86="A", 160000, B86="B", 130000) * _xlfn.IFS(D86="Entry (L3)", 0.8, D86="Mid (L4)", 1, D86="Senior (L5)", 1.4, D86="Staff (L6)", 1.8, D86="Principal (L7)", 2.5)} -> 280000
B87: S | D87: Staff (L6) | E87: {=_xlfn.IFS(B87="S", 200000, B87="A", 160000, B87="B", 130000) * _xlfn.IFS(D87="Entry (L3)", 0.8, D87="Mid (L4)", 1, D87="Senior (L5)", 1.4, D87="Staff (L6)", 1.8, D87="Principal (L7)", 2.5)} -> 360000
B88: S | D88: Principal (L7) | E88: {=_xlfn.IFS(B88="S", 200000, B88="A", 160000, B88="B", 130000) * _xlfn.IFS(D88="Entry (L3)", 0.8, D88="Mid (L4)", 1, D88="Senior (L5)", 1.4, D88="Staff (L6)", 1.8, D88="Principal (L7)", 2.5)} -> 500000
B89: S | C89: jumptrading | D89: Entry (L3) | E89: {=_xlfn.IFS(B89="S", 200000, B89="A", 160000, B89="B", 130000) * _xlfn.IFS(D89="Entry (L3)", 0.8, D89="Mid (L4)", 1, D89="Senior (L5)", 1.4, D89="Staff (L6)", 1.8, D89="Principal (L7)", 2.5)} -> 160000
B90: S | D90: Mid (L4) | E90: {=_xlfn.IFS(B90="S", 200000, B90="A", 160000, B90="B", 130000) * _xlfn.IFS(D90="Entry (L3)", 0.8, D90="Mid (L4)", 1, D90="Senior (L5)", 1.4, D90="Staff (L6)", 1.8, D90="Principal (L7)", 2.5)} -> 200000
B91: S | D91: Senior (L5) | E91: {=_xlfn.IFS(B91="S", 200000, B91="A", 160000, B91="B", 130000) * _xlfn.IFS(D91="Entry (L3)", 0.8, D91="Mid (L4)", 1, D91="Senior (L5)", 1.4, D91="Staff (L6)", 1.8, D91="Principal (L7)", 2.5)} -> 280000
B92: S | D92: Staff (L6) | E92: {=_xlfn.IFS(B92="S", 200000, B92="A", 160000, B92="B", 130000) * _xlfn.IFS(D92="Entry (L3)", 0.8, D92="Mid (L4)", 1, D92="Senior (L5)", 1.4, D92="Staff (L6)", 1.8, D92="Principal (L7)", 2.5)} -> 360000
B93: S | D93: Principal (L7) | E93: {=_xlfn.IFS(B93="S", 200000, B93="A", 160000, B93="B", 130000) * _xlfn.IFS(D93="Entry (L3)", 0.8, D93="Mid (L4)", 1, D93="Senior (L5)", 1.4, D93="Staff (L6)", 1.8, D93="Principal (L7)", 2.5)} -> 500000
B94: S | C94: Ridgewate | D94: Entry (L3) | E94: {=_xlfn.IFS(B94="S", 200000, B94="A", 160000, B94="B", 130000) * _xlfn.IFS(D94="Entry (L3)", 0.8, D94="Mid (L4)", 1, D94="Senior (L5)", 1.4, D94="Staff (L6)", 1.8, D94="Principal (L7)", 2.5)} -> 160000
B95: S | D95: Mid (L4) | E95: {=_xlfn.IFS(B95="S", 200000, B95="A", 160000, B95="B", 130000) * _xlfn.IFS(D95="Entry (L3)", 0.8, D95="Mid (L4)", 1, D95="Senior (L5)", 1.4, D95="Staff (L6)", 1.8, D95="Principal (L7)", 2.5)} -> 200000
B96: S | D96: Senior (L5) | E96: {=_xlfn.IFS(B96="S", 200000, B96="A", 160000, B96="B", 130000) * _xlfn.IFS(D96="Entry (L3)", 0.8, D96="Mid (L4)", 1, D96="Senior (L5)", 1.4, D96="Staff (L6)", 1.8, D96="Principal (L7)", 2.5)} -> 280000
B97: S | D97: Staff (L6) | E97: {=_xlfn.IFS(B97="S", 200000, B97="A", 160000, B97="B", 130000) * _xlfn.IFS(D97="Entry (L3)", 0.8, D97="Mid (L4)", 1, D97="Senior (L5)", 1.4, D97="Staff (L6)", 1.8, D97="Principal (L7)", 2.5)} -> 360000
B98: S | D98: Principal (L7) | E98: {=_xlfn.IFS(B98="S", 200000, B98="A", 160000, B98="B", 130000) * _xlfn.IFS(D98="Entry (L3)", 0.8, D98="Mid (L4)", 1, D98="Senior (L5)", 1.4, D98="Staff (L6)", 1.8, D98="Principal (L7)", 2.5)} -> 500000
B99: S | C99: Optiver | D99: Entry (L3) | E99: {=_xlfn.IFS(B99="S", 200000, B99="A", 160000, B99="B", 130000) * _xlfn.IFS(D99="Entry (L3)", 0.8, D99="Mid (L4)", 1, D99="Senior (L5)", 1.4, D99="Staff (L6)", 1.8, D99="Principal (L7)", 2.5)} -> 160000
B100: S | D100: Mid (L4) | E100: {=_xlfn.IFS(B100="S", 200000, B100="A", 160000, B100="B", 130000) * _xlfn.IFS(D100="Entry (L3)", 0.8, D100="Mid (L4)", 1, D100="Senior (L5)", 1.4, D100="Staff (L6)", 1.8, D100="Principal (L7)", 2.5)} -> 200000
B101: S | D101: Senior (L5) | E101: {=_xlfn.IFS(B101="S", 200000, B101="A", 160000, B101="B", 130000) * _xlfn.IFS(D101="Entry (L3)", 0.8, D101="Mid (L4)", 1, D101="Senior (L5)", 1.4, D101="Staff (L6)", 1.8, D101="Principal (L7)", 2.5)} -> 280000
B102: S | D102: Staff (L6) | E102: {=_xlfn.IFS(B102="S", 200000, B102="A", 160000, B102="B", 130000) * _xlfn.IFS(D102="Entry (L3)", 0.8, D102="Mid (L4)", 1, D102="Senior (L5)", 1.4, D102="Staff (L6)", 1.8, D102="Principal (L7)", 2.5)} -> 360000
B103: S | D103: Principal (L7) | E103: {=_xlfn.IFS(B103="S", 200000, B103="A", 160000, B103="B", 130000) * _xlfn.IFS(D103="Entry (L3)", 0.8, D103="Mid (L4)", 1, D103="Senior (L5)", 1.4, D103="Staff (L6)", 1.8, D103="Principal (L7)", 2.5)} -> 500000
B104: S | C104: Two Sigma | D104: Entry (L3) | E104: {=_xlfn.IFS(B104="S", 200000, B104="A", 160000, B104="B", 130000) * _xlfn.IFS(D104="Entry (L3)", 0.8, D104="Mid (L4)", 1, D104="Senior (L5)", 1.4, D104="Staff (L6)", 1.8, D104="Principal (L7)", 2.5)} -> 160000
B105: S | D105: Mid (L4) | E105: {=_xlfn.IFS(B105="S", 200000, B105="A", 160000, B105="B", 130000) * _xlfn.IFS(D105="Entry (L3)", 0.8, D105="Mid (L4)", 1, D105="Senior (L5)", 1.4, D105="Staff (L6)", 1.8, D105="Principal (L7)", 2.5)} -> 200000
B106: S | D106: Senior (L5) | E106: {=_xlfn.IFS(B106="S", 200000, B106="A", 160000, B106="B", 130000) * _xlfn.IFS(D106="Entry (L3)", 0.8, D106="Mid (L4)", 1, D106="Senior (L5)", 1.4, D106="Staff (L6)", 1.8, D106="Principal (L7)", 2.5)} -> 280000
B107: S | D107: Staff (L6) | E107: {=_xlfn.IFS(B107="S", 200000, B107="A", 160000, B107="B", 130000) * _xlfn.IFS(D107="Entry (L3)", 0.8, D107="Mid (L4)", 1, D107="Senior (L5)", 1.4, D107="Staff (L6)", 1.8, D107="Principal (L7)", 2.5)} -> 360000
B108: S | D108: Principal (L7) | E108: {=_xlfn.IFS(B108="S", 200000, B108="A", 160000, B108="B", 130000) * _xlfn.IFS(D108="Entry (L3)", 0.8, D108="Mid (L4)", 1, D108="Senior (L5)", 1.4, D108="Staff (L6)", 1.8, D108="Principal (L7)", 2.5)} -> 500000
B109: S | C109: DE Shaw&Co. | D109: Entry (L3) | E109: {=_xlfn.IFS(B109="S", 200000, B109="A", 160000, B109="B", 130000) * _xlfn.IFS(D109="Entry (L3)", 0.8, D109="Mid (L4)", 1, D109="Senior (L5)", 1.4, D109="Staff (L6)", 1.8, D109="Principal (L7)", 2.5)} -> 160000
B110: S | D110: Mid (L4) | E110: {=_xlfn.IFS(B110="S", 200000, B110="A", 160000, B110="B", 130000) * _xlfn.IFS(D110="Entry (L3)", 0.8, D110="Mid (L4)", 1, D110="Senior (L5)", 1.4, D110="Staff (L6)", 1.8, D110="Principal (L7)", 2.5)} -> 200000
B111: S | D111: Senior (L5) | E111: {=_xlfn.IFS(B111="S", 200000, B111="A", 160000, B111="B", 130000) * _xlfn.IFS(D111="Entry (L3)", 0.8, D111="Mid (L4)", 1, D111="Senior (L5)", 1.4, D111="Staff (L6)", 1.8, D111="Principal (L7)", 2.5)} -> 280000
B112: S | D112: Staff (L6) | E112: {=_xlfn.IFS(B112="S", 200000, B112="A", 160000, B112="B", 130000) * _xlfn.IFS(D112="Entry (L3)", 0.8, D112="Mid (L4)", 1, D112="Senior (L5)", 1.4, D112="Staff (L6)", 1.8, D112="Principal (L7)", 2.5)} -> 360000
B113: S | D113: Principal (L7) | E113: {=_xlfn.IFS(B113="S", 200000, B113="A", 160000, B113="B", 130000) * _xlfn.IFS(D113="Entry (L3)", 0.8, D113="Mid (L4)", 1, D113="Senior (L5)", 1.4, D113="Staff (L6)", 1.8, D113="Principal (L7)", 2.5)} -> 500000
B114: S | C114: Five Rings | D114: Entry (L3) | E114: {=_xlfn.IFS(B114="S", 200000, B114="A", 160000, B114="B", 130000) * _xlfn.IFS(D114="Entry (L3)", 0.8, D114="Mid (L4)", 1, D114="Senior (L5)", 1.4, D114="Staff (L6)", 1.8, D114="Principal (L7)", 2.5)} -> 160000
B115: S | D115: Mid (L4) | E115: {=_xlfn.IFS(B115="S", 200000, B115="A", 160000, B115="B", 130000) * _xlfn.IFS(D115="Entry (L3)", 0.8, D115="Mid (L4)", 1, D115="Senior (L5)", 1.4, D115="Staff (L6)", 1.8, D115="Principal (L7)", 2.5)} -> 200000
B116: S | D116: Senior (L5) | E116: {=_xlfn.IFS(B116="S", 200000, B116="A", 160000, B116="B", 130000) * _xlfn.IFS(D116="Entry (L3)", 0.8, D116="Mid (L4)", 1, D116="Senior (L5)", 1.4, D116="Staff (L6)", 1.8, D116="Principal (L7)", 2.5)} -> 280000
B117: S | D117: Staff (L6) | E117: {=_xlfn.IFS(B117="S", 200000, B117="A", 160000, B117="B", 130000) * _xlfn.IFS(D117="Entry (L3)", 0.8, D117="Mid (L4)", 1, D117="Senior (L5)", 1.4, D117="Staff (L6)", 1.8, D117="Principal (L7)", 2.5)} -> 360000
B118: S | D118: Principal (L7) | E118: {=_xlfn.IFS(B118="S", 200000, B118="A", 160000, B118="B", 130000) * _xlfn.IFS(D118="Entry (L3)", 0.8, D118="Mid (L4)", 1, D118="Senior (L5)", 1.4, D118="Staff (L6)", 1.8, D118="Principal (L7)", 2.5)} -> 500000
B119: S | C119: XTX | D119: Entry (L3) | E119: {=_xlfn.IFS(B119="S", 200000, B119="A", 160000, B119="B", 130000) * _xlfn.IFS(D119="Entry (L3)", 0.8, D119="Mid (L4)", 1, D119="Senior (L5)", 1.4, D119="Staff (L6)", 1.8, D119="Principal (L7)", 2.5)} -> 160000
B120: S | D120: Mid (L4) | E120: {=_xlfn.IFS(B120="S", 200000, B120="A", 160000, B120="B", 130000) * _xlfn.IFS(D120="Entry (L3)", 0.8, D120="Mid (L4)", 1, D120="Senior (L5)", 1.4, D120="Staff (L6)", 1.8, D120="Principal (L7)", 2.5)} -> 200000
B121: S | D121: Senior (L5) | E121: {=_xlfn.IFS(B121="S", 200000, B121="A", 160000, B121="B", 130000) * _xlfn.IFS(D121="Entry (L3)", 0.8, D121="Mid (L4)", 1, D121="Senior (L5)", 1.4, D121="Staff (L6)", 1.8, D121="Principal (L7)", 2.5)} -> 280000
B122: S | D122: Staff (L6) | E122: {=_xlfn.IFS(B122="S", 200000, B122="A", 160000, B122="B", 130000) * _xlfn.IFS(D122="Entry (L3)", 0.8, D122="Mid (L4)", 1, D122="Senior (L5)", 1.4, D122="Staff (L6)", 1.8, D122="Principal (L7)", 2.5)} -> 360000
B123: S | D123: Principal (L7) | E123: {=_xlfn.IFS(B123="S", 200000, B123="A", 160000, B123="B", 130000) * _xlfn.IFS(D123="Entry (L3)", 0.8, D123="Mid (L4)", 1, D123="Senior (L5)", 1.4, D123="Staff (L6)", 1.8, D123="Principal (L7)", 2.5)} -> 500000
B124: S | C124: imc | D124: Entry (L3) | E124: {=_xlfn.IFS(B124="S", 200000, B124="A", 160000, B124="B", 130000) * _xlfn.IFS(D124="Entry (L3)", 0.8, D124="Mid (L4)", 1, D124="Senior (L5)", 1.4, D124="Staff (L6)", 1.8, D124="Principal (L7)", 2.5)} -> 160000
B125: S | D125: Mid (L4) | E125: {=_xlfn.IFS(B125="S", 200000, B125="A", 160000, B125="B", 130000) * _xlfn.IFS(D125="Entry (L3)", 0.8, D125="Mid (L4)", 1, D125="Senior (L5)", 1.4, D125="Staff (L6)", 1.8, D125="Principal (L7)", 2.5)} -> 200000
B126: S | D126: Senior (L5) | E126: {=_xlfn.IFS(B126="S", 200000, B126="A", 160000, B126="B", 130000) * _xlfn.IFS(D126="Entry (L3)", 0.8, D126="Mid (L4)", 1, D126="Senior (L5)", 1.4, D126="Staff (L6)", 1.8, D126="Principal (L7)", 2.5)} -> 280000
B127: S | D127: Staff (L6) | E127: {=_xlfn.IFS(B127="S", 200000, B127="A", 160000, B127="B", 130000) * _xlfn.IFS(D127="Entry (L3)", 0.8, D127="Mid (L4)", 1, D127="Senior (L5)", 1.4, D127="Staff (L6)", 1.8, D127="Principal (L7)", 2.5)} -> 360000
B128: S | D128: Principal (L7) | E128: {=_xlfn.IFS(B128="S", 200000, B128="A", 160000, B128="B", 130000) * _xlfn.IFS(D128="Entry (L3)", 0.8, D128="Mid (L4)", 1, D128="Senior (L5)", 1.4, D128="Staff (L6)", 1.8, D128="Principal (L7)", 2.5)} -> 500000
B129: S | C129: Anthropic | D129: Entry (L3) | E129: {=_xlfn.IFS(B129="S", 200000, B129="A", 160000, B129="B", 130000) * _xlfn.IFS(D129="Entry (L3)", 0.8, D129="Mid (L4)", 1, D129="Senior (L5)", 1.4, D129="Staff (L6)", 1.8, D129="Principal (L7)", 2.5)} -> 160000
B130: S | D130: Mid (L4) | E130: {=_xlfn.IFS(B130="S", 200000, B130="A", 160000, B130="B", 130000) * _xlfn.IFS(D130="Entry (L3)", 0.8, D130="Mid (L4)", 1, D130="Senior (L5)", 1.4, D130="Staff (L6)", 1.8, D130="Principal (L7)", 2.5)} -> 200000
B131: S | D131: Senior (L5) | E131: {=_xlfn.IFS(B131="S", 200000, B131="A", 160000, B131="B", 130000) * _xlfn.IFS(D131="Entry (L3)", 0.8, D131="Mid (L4)", 1, D131="Senior (L5)", 1.4, D131="Staff (L6)", 1.8, D131="Principal (L7)", 2.5)} -> 280000
B132: S | D132: Staff (L6) | E132: {=_xlfn.IFS(B132="S", 200000, B132="A", 160000, B132="B", 130000) * _xlfn.IFS(D132="Entry (L3)", 0.8, D132="Mid (L4)", 1, D132="Senior (L5)", 1.4, D132="Staff (L6)", 1.8, D132="Principal (L7)", 2.5)} -> 360000
...

Sheet Valuation
B2: Valuation Sheet
B3: Gross TC | C3: $ | D3: =Assumptions!E11*(1+Assumptions!E12/100)+Assumptions!E13+Assumptions!E14 -> 234700
B4: Tax | C4: $ | D4: {=_xlfn.IFS( Assumptions!E9=Market_Comps!V4, _xlfn.XLOOKUP(Valuation!D3, Market_Comps!V5:V11, Market_Comps!X5:X11, , -1) + (Valuation!D3 - _xlfn.XLOOKUP(Valuation!D3, Market_Comps!V5:V11, Market_Comps!V5:V11, , -1)) * _xlfn.XLOOKUP(Valuation!D3, Market_Comps!V5:V11, Market_Comps!W5:W11, , -1), Assumptions!E9=Market_Comps!V12, _xlfn.XLOOKUP(Valuation!D3, Market_Comps!V14:V20, Market_Comps!X14:X20, , -1) + (Valuation!D3 - _xlfn.XLOOKUP(Valuation!D3, Market_Comps!V14:V20, Market_Comps!V14:V20, , -1)) * _xlfn.XLOOKUP(Valuation!D3, Market_Comps!V14:V20, Market_Comps!W14:W20, , -1), Assumptions!E9=Market_Comps!V21, _xlfn.XLOOKUP(Valuation!D3, Market_Comps!V22:V28, Market_Comps!X22:X28, , -1) + (Valuation!D3 - _xlfn.XLOOKUP(Valuation!D3, Market_Comps!V22:V28, Market_Comps!V22:V28, , -1)) * _xlfn.XLOOKUP(Valuation!D3, Market_Comps!V22:V28, Market_Comps!W22:W28, , -1) )} -> 9.3693845e+09
B5: Net TC | C5: $ | D5: =D3*Market_Comps!T4 -> 145514
B7: Standard Level | C7: Level | D7: {=_xlfn.XLOOKUP(Assumptions!E5&Assumptions!E6, Market_Comps!J:J&Market_Comps!K:K, Market_Comps!L:L, "Error")} -> Senior (L5)
B8: Market Company Gross TC | C8: $ | D8: =SUMIFS(Market_Comps!E:E, Market_Comps!C:C, Assumptions!E5, Market_Comps!D:D, D7) -> 256607
B9: Market Gross TC | C9: $ | D9: =AVERAGEIFS(Market_Comps!E:E, Market_Comps!D:D, Valuation!D7) -> 258488.94
B11: Annual Living Cost | C11: $ | D11: =(IF(Assumptions!E18<>"",Assumptions!E18,_xlfn.XLOOKUP(Assumptions!E16,Market_Comps!N:N,Market_Comps!O:O))+IF(Assumptions!E19<>"",Assumptions!E19,_xlfn.XLOOKUP(Assumptions!E16,Market_Comps!N:N,Market_Comps!P:P)*_xlfn.XLOOKUP(Assumptions!E16,Market_Comps!N:N,Market_Comps!Q:Q))*12) -> 1748
B13: Annual Working days | C13: Days | D13: =250-Assumptions!E23 -> 233
B15: True Annual Working Hours | C15: Hours | D15: =(Assumptions!E22/5*D13)+(Assumptions!E19*Assumptions!E20*52)-(Assumptions!E20*Assumptions!E23) -> 2482.8
B17: Hourly Wage | C17: $/Hour | D17: =D5/D15 -> 58.608829
B19: Financial Score | D19: =(D3/((0.8*D8)+(0.2*D9)))*100 -> 91.328861
B20: WLB Score | D20: =(Market_Comps!T6/D15)*100 -> 83.776382
B21: Company Vibe Score | D21: =AVERAGE(Assumptions!E24:E26)/5*100 -> 80
B23: Job Value Index | D23: =(Valuation!D19*(Assumptions!E28/100)+Valuation!D20*(Assumptions!E29/100)+Valuation!D21*(Valuation!E29/100))/96*100 -> 82.473941

Sheet Interface
B3: Job Value Data
B4: JVI Index | D4: =Valuation!D23 -> 82.473941
B5: True Hourly Salary | D5: =Valuation!D17 -> 58.608829
B6: Gross TC | D6: =Valuation!D3 -> 234700
B7: Net TC | D7: =Valuation!D5 -> 145514
